updatexplorer/__init__.py
updatexplorer/main.py
updatexplorer/prompts.py
updatexplorer-2025.12.21083607.dist-info/METADATA
updatexplorer-2025.12.21083607.dist-info/WHEEL
updatexplorer-2025.12.21083607.dist-info/top_level.txt
updatexplorer-2025.12.21083607.dist-info/RECORD
