Metadata-Version: 2.4
Name: updatexplorer
Version: 2025.12.21083607
Summary: A new package designed to interpret and extract structured technical insights from user-submitted hardware and software update summaries. It processes concise text inputs about hardware support change
Author-email: updatexplorer <hi@eugene.plus>
License: MIT
Project-URL: Homepage, https://github.com/chigwell/updatexplorer
Requires-Python: >=3.9
Requires-Dist: langchain-llm7>=0.0.0
Requires-Dist: llmatch-messages>=0.0.0
Requires-Dist: langchain-core>=0.3.0
